x8/_common/__init__.py
x8/_common/azure_provider.py
x8/_common/google_provider.py
x8/_common/hosted_provider.py
x8/_common/redis_provider.py
x8/ai/_common/openai_provider.py
x8/ai/text_generation/__init__.py
x8/ai/text_generation/_models.py
x8/ai/text_generation/component.py
x8/ai/text_generation/providers/google.py
x8/ai/text_generation/providers/openai.py
x8/ai/video_generation/__init__.py
x8/ai/video_generation/_models.py
x8/ai/video_generation/component.py
x8/ai/video_generation/providers/api.py
x8/ai/video_generation/providers/google.py
x8/ai/video_generation/providers/lumaai.py
x8/ai/video_generation/providers/minimax.py
x8/ai/video_generation/providers/openai.py
x8/ai/video_generation/providers/runwayml.py
x8/composite/choice/__init__.py
x8/composite/choice/_models.py
x8/composite/choice/component.py
x8/composite/choice/providers/default.py
x8/composite/script/__init__.py
x8/composite/script/component.py
x8/composite/script/providers/default.py
x8/compute/_common/_amazon_ec2_helper.py
x8/compute/_common/_image_helper.py
x8/compute/_common/_models.py
x8/compute/container_deployment/__init__.py
x8/compute/container_deployment/_feature.py
x8/compute/container_deployment/_helper.py
x8/compute/container_deployment/_models.py
x8/compute/container_deployment/component.py
x8/compute/container_deployment/py.typed
x8/compute/container_deployment/providers/_amazon_ecs.py
x8/compute/container_deployment/providers/_base.py
x8/compute/container_deployment/providers/amazon_ecs_ec2.py
x8/compute/container_deployment/providers/amazon_ecs_fargate.py
x8/compute/container_deployment/providers/aws_app_runner.py
x8/compute/container_deployment/providers/azure_container_apps.py
x8/compute/container_deployment/providers/azure_container_instances.py
x8/compute/container_deployment/providers/default.py
x8/compute/container_deployment/providers/docker_local.py
x8/compute/container_deployment/providers/google_cloud_run.py
x8/compute/container_deployment/providers/local.py
x8-0.0.11.dist-info/METADATA
x8-0.0.11.dist-info/WHEEL
x8-0.0.11.dist-info/entry_points.txt
x8-0.0.11.dist-info/licenses/LICENSE
x8-0.0.11.dist-info/RECORD
